LICENSE
README.md
setup.py
testflows.core.egg-info/PKG-INFO
testflows.core.egg-info/SOURCES.txt
testflows.core.egg-info/dependency_links.txt
testflows.core.egg-info/not-zip-safe
testflows.core.egg-info/requires.txt
testflows.core.egg-info/top_level.txt
testflows/_core/__init__.py
testflows/_core/baseobject.py
testflows/_core/compress.py
testflows/_core/constants.py
testflows/_core/exceptions.py
testflows/_core/filters.py
testflows/_core/flags.py
testflows/_core/funcs.py
testflows/_core/has.py
testflows/_core/init.py
testflows/_core/io.py
testflows/_core/jupyter_notebook.py
testflows/_core/message.py
testflows/_core/name.py
testflows/_core/objects.py
testflows/_core/serialize.py
testflows/_core/temp.py
testflows/_core/test.py
testflows/_core/testtype.py
testflows/_core/tracing.py
testflows/_core/bin/tfs
testflows/_core/bin/tfs-worker
testflows/_core/cli/__init__.py
testflows/_core/cli/colors.py
testflows/_core/cli/text.py
testflows/_core/cli/arg/__init__.py
testflows/_core/cli/arg/common.py
testflows/_core/cli/arg/exit.py
testflows/_core/cli/arg/parser.py
testflows/_core/cli/arg/type.py
testflows/_core/cli/arg/handlers/__init__.py
testflows/_core/cli/arg/handlers/handler.py
testflows/_core/cli/arg/handlers/log.py
testflows/_core/cli/arg/handlers/run.py
testflows/_core/cli/arg/handlers/document/__init__.py
testflows/_core/cli/arg/handlers/document/convert.py
testflows/_core/cli/arg/handlers/document/handler.py
testflows/_core/cli/arg/handlers/document/toc.py
testflows/_core/cli/arg/handlers/document/new/__init__.py
testflows/_core/cli/arg/handlers/document/new/handler.py
testflows/_core/cli/arg/handlers/document/new/requirements.py
testflows/_core/cli/arg/handlers/report/__init__.py
testflows/_core/cli/arg/handlers/report/copyright.py
testflows/_core/cli/arg/handlers/report/coverage.py
testflows/_core/cli/arg/handlers/report/handler.py
testflows/_core/cli/arg/handlers/report/metrics.py
testflows/_core/cli/arg/handlers/report/results.py
testflows/_core/cli/arg/handlers/report/specification.py
testflows/_core/cli/arg/handlers/report/srs_coverage.py
testflows/_core/cli/arg/handlers/report/tracebility.py
testflows/_core/cli/arg/handlers/report/compare/__init__.py
