Metadata-Version: 2.1
Name: testflows.core
Version: 2.0.250110.1002922
Summary: TestFlows - Core
Home-page: https://github.com/testflows/testflows-core
Author: Vitaliy Zakaznikov
Author-email: vzakaznikov@testflows.com
License: Apache-2.0
Classifier: Development Status :: 2 - Pre-Alpha
Classifier: Programming Language :: Python :: 3
Classifier: License :: OSI Approved :: Apache Software License
Classifier: Operating System :: POSIX :: Linux
Requires-Python: >=3.8
License-File: LICENSE
Provides-Extra: dev
